catencfamily/__init__.py
catencfamily/encoders.py
catencfamily/mergeLevels.py
catencfamily/utils.py
catencfamily-0.1.19.dist-info/METADATA
catencfamily-0.1.19.dist-info/WHEEL
catencfamily-0.1.19.dist-info/licenses/LICENSE
catencfamily-0.1.19.dist-info/RECORD
