Metadata-Version: 2.1
Name: catencfamily
Version: 0.1.19
Summary: A class to generate a family of categorical encoders using network analysis
Project-URL: Homepage, https://github.com/harnalashok/CatEncodersFamily
Author-email: Ashok Kumar Harnal <ashokharnal@gmail.com>
License-File: LICENSE
Classifier: License :: OSI Approved :: MIT License
Classifier: Operating System :: OS Independent
Classifier: Programming Language :: Python :: 3
Requires-Python: >=3.7
Requires-Dist: cdlib
Requires-Dist: matplotlib
Requires-Dist: networkx
Requires-Dist: numpy
Requires-Dist: pandas
Requires-Dist: pathlib
Requires-Dist: scikit-learn
Requires-Dist: scipy
Requires-Dist: seaborn
